renovosolutions_certbot/__init__.py
renovosolutions_certbot/py.typed
renovosolutions_certbot/_jsii/__init__.py
renovosolutions_certbot/_jsii/cdk-library-certbot@2.9.2.jsii.tgz
renovosolutions_aws_cdk_certbot-2.9.2.dist-info/LICENSE
renovosolutions_aws_cdk_certbot-2.9.2.dist-info/METADATA
renovosolutions_aws_cdk_certbot-2.9.2.dist-info/WHEEL
renovosolutions_aws_cdk_certbot-2.9.2.dist-info/top_level.txt
renovosolutions_aws_cdk_certbot-2.9.2.dist-info/RECORD
